lightbulb/ext/filament/__init__.py
lightbulb/ext/filament/__main__.py
lightbulb/ext/filament/_t/__init__.py
lightbulb/ext/filament/_t/filament_bot.nsx
lightbulb/ext/filament/_t/lightbulb_bot.nsx
lightbulb/ext/filament/_t/unlicense.txt
lightbulb/ext/filament/commands/__init__.py
lightbulb/ext/filament/commands/impl.py
lightbulb/ext/filament/exts/__init__.py
lightbulb/ext/filament/exts/superuser.py
lightbulb/ext/filament/utils/__init__.py
lightbulb/ext/filament/utils/misc.py
lightbulb/ext/filament/utils/shorthand.py
lightbulb_ext_filament-0.1.2.post0.dist-info/COPYING.LESSER.md
lightbulb_ext_filament-0.1.2.post0.dist-info/COPYING.md
lightbulb_ext_filament-0.1.2.post0.dist-info/METADATA
lightbulb_ext_filament-0.1.2.post0.dist-info/WHEEL
lightbulb_ext_filament-0.1.2.post0.dist-info/top_level.txt
lightbulb_ext_filament-0.1.2.post0.dist-info/RECORD
