Metadata-Version: 2.1
Name: lightbulb-ext-filament
Version: 0.1.2.post0
Summary: Various add-ons, extensions and utilities for hikari-lightbulb
Home-page: https://github.com/tandemdude/filament
Author: tandemdude
Author-email: tandemdude1@gmail.com
License: LGPL-3.0-ONLY
Classifier: Development Status :: 3 - Alpha
Classifier: Framework :: AsyncIO
Classifier: Intended Audience :: Developers
Classifier: Natural Language :: English
Classifier: Topic :: Software Development :: Libraries :: Python Modules
Classifier: Programming Language :: Python :: 3.8
Classifier: Programming Language :: Python :: 3.9
Classifier: Programming Language :: Python :: 3.10
Classifier: Programming Language :: Python :: Implementation :: CPython
Classifier: Programming Language :: Python :: 3 :: Only
Classifier: Topic :: Software Development :: Libraries
Classifier: Topic :: Software Development :: Libraries :: Application Frameworks
Classifier: Topic :: Software Development :: Libraries :: Python Modules
Requires-Python: >=3.8.0,<3.11
License-File: COPYING.LESSER.md
License-File: COPYING.md
